egyptian_id_validator/__init__.py
egyptian_id_validator/generation.py
egyptian_id_validator/validation.py
egyptian_id_validator-0.4.4.dist-info/licenses/LICENSE.md
egyptian_id_validator-0.4.4.dist-info/METADATA
egyptian_id_validator-0.4.4.dist-info/WHEEL
egyptian_id_validator-0.4.4.dist-info/top_level.txt
egyptian_id_validator-0.4.4.dist-info/RECORD
