Metadata-Version: 2.4
Name: egyptian-id-validator
Version: 0.4.4
Summary: A Python package for validating Egyptian National IDs.
Author-email: "Mohamed A. Abdallah" <eng.mohamed.a.abdallah@gmail.com>
License-Expression: LicenseRef-MIT-Custom
Project-URL: Homepage, https://github.com/MohamedAAbdallah/Egyptian-ID-Validator
Project-URL: Repository, https://github.com/MohamedAAbdallah/Egyptian-ID-Validator-Py
Project-URL: Issues, https://github.com/MohamedAAbdallah/Egyptian-ID-Validator-Py/issues
Keywords: egypt,national-id,validator,egyptian,citizen-id
Classifier: Development Status :: 5 - Production/Stable
Classifier: Intended Audience :: Developers
Classifier: Topic :: Software Development :: Libraries :: Python Modules
Classifier: Programming Language :: Python :: 3
Classifier: Programming Language :: Python :: 3.8
Classifier: Programming Language :: Python :: 3.9
Classifier: Programming Language :: Python :: 3.10
Classifier: Programming Language :: Python :: 3.11
Classifier: Programming Language :: Python :: 3.12
Requires-Python: >=3.8
License-File: LICENSE.md
Provides-Extra: dev
Requires-Dist: pytest; extra == "dev"
Requires-Dist: flake8; extra == "dev"
Requires-Dist: build; extra == "dev"
Requires-Dist: twine; extra == "dev"
Dynamic: license-file
